gke_pod_snapshots_tools/__init__.py
gke_pod_snapshots_tools/core.py
gke_pod_snapshots_tools-0.1.0.dist-info/licenses/LICENSE
gke_pod_snapshots_tools-0.1.0.dist-info/METADATA
gke_pod_snapshots_tools-0.1.0.dist-info/WHEEL
gke_pod_snapshots_tools-0.1.0.dist-info/top_level.txt
gke_pod_snapshots_tools-0.1.0.dist-info/RECORD
