Metadata-Version: 2.4
Name: gke-pod-snapshots-tools
Version: 0.1.0
Summary: A lightweight utility to integrate with GKE Pod snapshots for fast startup.
License: Apache-2.0
Project-URL: Homepage, https://github.com/codersherlock/gke-pod-snapshots-tools
Project-URL: Bug Tracker, https://github.com/codersherlock/gke-pod-snapshots-tools/issues
Classifier: Programming Language :: Python :: 3
Classifier: License :: OSI Approved :: Apache Software License
Classifier: Operating System :: OS Independent
Classifier: Topic :: System :: Distributed Computing
Requires-Python: >=3.7
License-File: LICENSE
Dynamic: license-file
